{
    "group": "М3О-212Б-23",
    "28.10.2024": {
        "day": "Пн",
        "pairs": {
            "10:45:00": {
                "Основы психологии": {
                    "time_start": "10:45:00",
                    "time_end": "12:15:00",
                    "lector": {
                        "7b85f9fe-66a7-11ef-bc20-3cecef1c132f": "Ширяева Виктория Валерьевна"
                    },
                    "type": {
                        "ЛК": 1
                    },
                    "room": {
                        "c493ff36-07bb-11e0-bf99-003048ccec9b": "3-435"
                    },
                    "lms": "",
                    "teams": "",
                    "other": ""
                }
            },
            "13:00:00": {
                "Общая физика": {
                    "time_start": "13:00:00",
                    "time_end": "14:30:00",
                    "lector": {
                        "00000000-0000-0000-0000-000000000000": ""
                    },
                    "type": {
                        "ПЗ": 1
                    },
                    "room": {
                        "4cff9e68-02fa-11e0-bf99-003048ccec9b": "3-111"
                    },
                    "lms": "",
                    "teams": "",
                    "other": ""
                }
            },
            "14:45:00": {
                "Основы психологии": {
                    "time_start": "14:45:00",
                    "time_end": "16:15:00",
                    "lector": {
                        "d49dfc75-0d8e-11e4-b897-005056c00008": "АВАНЕСЯН ГАНА ГЕОРГИЕВНА"
                    },
                    "type": {
                        "ПЗ": 1
                    },
                    "room": {
                        "c493ff32-07bb-11e0-bf99-003048ccec9b": "3-445"
                    },
                    "lms": "",
                    "teams": "",
                    "other": ""
                }
            },
            "16:30:00": {
                "Дифференциальные уравнения": {
                    "time_start": "16:30:00",
                    "time_end": "18:00:00",
                    "lector": {
                        "966bef77-1d99-11e0-9baf-1c6f65450efa": "Вестяк Владимир Анатольевич"
                    },
                    "type": {
                        "ЛК": 1
                    },
                    "room": {
                        "6b63edb1-6a04-11e6-ba19-003048dec27f": "ГУК В-221"
                    },
                    "lms": "",
                    "teams": "",
                    "other": ""
                }
            }
        }
    },
    "29.10.2024": {
        "day": "Вт",
        "pairs": {
            "9:00:00": {
                "Базы данных": {
                    "time_start": "9:00:00",
                    "time_end": "10:30:00",
                    "lector": {
                        "5eb7f01c-1d99-11e0-9baf-1c6f65450efa": "Склеймин Юрий Борисович"
                    },
                    "type": {
                        "ЛК": 1
                    },
                    "room": {
                        "c493ff2a-07bb-11e0-bf99-003048ccec9b": "3-404"
                    },
                    "lms": "",
                    "teams": "",
                    "other": ""
                }
            },
            "10:45:00": {
                "Общая физика": {
                    "time_start": "10:45:00",
                    "time_end": "12:15:00",
                    "lector": {
                        "00000000-0000-0000-0000-000000000000": ""
                    },
                    "type": {
                        "ЛК": 1
                    },
                    "room": {
                        "2ea00f14-7722-11e0-a630-003048ccec9b": "ГУК В-228"
                    },
                    "lms": "",
                    "teams": "",
                    "other": ""
                }
            },
            "13:00:00": {
                "Физическая культура": {
                    "time_start": "13:00:00",
                    "time_end": "14:30:00",
                    "lector": {
                        "00000000-0000-0000-0000-000000000000": ""
                    },
                    "type": {
                        "ПЗ": 1
                    },
                    "room": {
                        "9bd25e78-5fc5-11ef-bc20-3cecef1c132f": "--каф. 919"
                    },
                    "lms": "",
                    "teams": "",
                    "other": ""
                }
            },
            "16:30:00": {
                "Иностранный язык": {
                    "time_start": "16:30:00",
                    "time_end": "18:00:00",
                    "lector": {
                        "00000000-0000-0000-0000-000000000000": ""
                    },
                    "type": {
                        "ПЗ": 1
                    },
                    "room": {
                        "0285fcb2-037f-11e0-bf99-003048ccec9b": "3-346"
                    },
                    "lms": "",
                    "teams": "",
                    "other": ""
                }
            }
        }
    },
    "30.10.2024": {
        "day": "Ср",
        "pairs": {
            "9:00:00": {
                "Дифференциальные уравнения": {
                    "time_start": "9:00:00",
                    "time_end": "10:30:00",
                    "lector": {
                        "1d03efbb-4303-11e0-8d72-00137240fb25": "Богданова Софья Борисовна",
                        "79d4645e-1d99-11e0-9baf-1c6f65450efa": "Григоревский Николай Владимирович"
                    },
                    "type": {
                        "ПЗ": 1
                    },
                    "room": {
                        "ec99efc9-0302-11e0-bf99-003048ccec9b": "3-232"
                    },
                    "lms": "",
                    "teams": "",
                    "other": ""
                }
            },
            "10:45:00": {
                "Программирование на языках высокого уровня": {
                    "time_start": "10:45:00",
                    "time_end": "12:15:00",
                    "lector": {
                        "034d4bb8-8618-11e6-b2eb-3cd92bf20bfe": "ПАВЛОВ ОЛЕГ ВЛАДИМИРОВИЧ"
                    },
                    "type": {
                        "ПЗ": 1
                    },
                    "room": {
                        "bfb44310-7944-11e8-82e6-003048dec27f": "3-420"
                    },
                    "lms": "",
                    "teams": "",
                    "other": ""
                }
            },
            "13:00:00": {
                "Схемотехника": {
                    "time_start": "13:00:00",
                    "time_end": "14:30:00",
                    "lector": {
                        "def5dabd-38b5-11ed-bbea-ac1f6b64c5eb": "Лукошин Илья Владимирович"
                    },
                    "type": {
                        "ПЗ": 1
                    },
                    "room": {
                        "87ec3d54-e648-11e7-8335-003048dec27f": "3-365"
                    },
                    "lms": "",
                    "teams": "",
                    "other": ""
                }
            },
            "14:45:00": {
                "Схемотехника": {
                    "time_start": "14:45:00",
                    "time_end": "16:15:00",
                    "lector": {
                        "def5dabd-38b5-11ed-bbea-ac1f6b64c5eb": "Лукошин Илья Владимирович"
                    },
                    "type": {
                        "ПЗ": 1
                    },
                    "room": {
                        "87ec3d54-e648-11e7-8335-003048dec27f": "3-365"
                    },
                    "lms": "",
                    "teams": "",
                    "other": ""
                }
            }
        }
    },
    "31.10.2024": {
        "day": "Чт",
        "pairs": {
            "9:00:00": {
                "Физическая культура": {
                    "time_start": "9:00:00",
                    "time_end": "10:30:00",
                    "lector": {
                        "00000000-0000-0000-0000-000000000000": ""
                    },
                    "type": {
                        "ПЗ": 1
                    },
                    "room": {
                        "9bd25e78-5fc5-11ef-bc20-3cecef1c132f": "--каф. 919"
                    },
                    "lms": "",
                    "teams": "",
                    "other": ""
                }
            },
            "13:00:00": {
                "Общая физика": {
                    "time_start": "13:00:00",
                    "time_end": "14:30:00",
                    "lector": {
                        "00000000-0000-0000-0000-000000000000": ""
                    },
                    "type": {
                        "ЛР": 1
                    },
                    "room": {
                        "4e16fc2b-aa98-11e6-8e0c-003048dec27f": "Орш. В-605"
                    },
                    "lms": "",
                    "teams": "",
                    "other": ""
                }
            },
            "14:45:00": {
                "Общая физика": {
                    "time_start": "14:45:00",
                    "time_end": "16:15:00",
                    "lector": {
                        "00000000-0000-0000-0000-000000000000": ""
                    },
                    "type": {
                        "ЛР": 1
                    },
                    "room": {
                        "4e16fc2b-aa98-11e6-8e0c-003048dec27f": "Орш. В-605"
                    },
                    "lms": "",
                    "teams": "",
                    "other": ""
                }
            }
        }
    },
    "01.11.2024": {
        "day": "Пт",
        "pairs": {
            "9:00:00": {
                "Военная подготовка": {
                    "time_start": "9:00:00",
                    "time_end": "10:30:00",
                    "lector": {
                        "00000000-0000-0000-0000-000000000000": ""
                    },
                    "type": {
                        "ПЗ": 1
                    },
                    "room": {
                        "b74722b0-6af3-11e6-ba19-003048dec27f": "--каф."
                    },
                    "lms": "",
                    "teams": "",
                    "other": ""
                }
            },
            "10:45:00": {
                "Военная подготовка": {
                    "time_start": "10:45:00",
                    "time_end": "12:15:00",
                    "lector": {
                        "00000000-0000-0000-0000-000000000000": ""
                    },
                    "type": {
                        "ПЗ": 1
                    },
                    "room": {
                        "b74722b0-6af3-11e6-ba19-003048dec27f": "--каф."
                    },
                    "lms": "",
                    "teams": "",
                    "other": ""
                }
            },
            "13:00:00": {
                "Военная подготовка": {
                    "time_start": "13:00:00",
                    "time_end": "14:30:00",
                    "lector": {
                        "00000000-0000-0000-0000-000000000000": ""
                    },
                    "type": {
                        "ПЗ": 1
                    },
                    "room": {
                        "b74722b0-6af3-11e6-ba19-003048dec27f": "--каф."
                    },
                    "lms": "",
                    "teams": "",
                    "other": ""
                }
            },
            "14:45:00": {
                "Военная подготовка": {
                    "time_start": "14:45:00",
                    "time_end": "16:15:00",
                    "lector": {
                        "00000000-0000-0000-0000-000000000000": ""
                    },
                    "type": {
                        "ПЗ": 1
                    },
                    "room": {
                        "b74722b0-6af3-11e6-ba19-003048dec27f": "--каф."
                    },
                    "lms": "",
                    "teams": "",
                    "other": ""
                }
            }
        }
    },
    "02.11.2024": {
        "day": "Сб",
        "pairs": {
            "13:00:00": {
                "Иностранный язык": {
                    "time_start": "13:00:00",
                    "time_end": "14:30:00",
                    "lector": {
                        "00000000-0000-0000-0000-000000000000": ""
                    },
                    "type": {
                        "ПЗ": 1
                    },
                    "room": {
                        "ec99efc9-0302-11e0-bf99-003048ccec9b": "3-232"
                    },
                    "lms": "",
                    "teams": "",
                    "other": ""
                }
            }
        }
    }
}
